funciones.py
asir_antonio_irles_2-0.0.2.dist-info/METADATA
asir_antonio_irles_2-0.0.2.dist-info/WHEEL
asir_antonio_irles_2-0.0.2.dist-info/licenses/LICENSE
asir_antonio_irles_2-0.0.2.dist-info/RECORD
