Metadata-Version: 2.1
Name: asir_Antonio_Irles_2
Version: 0.0.2
Summary: Ejemplo de como crear un paquete
Project-URL: Homepage, https://github.com/antoniobaia2/clase
Project-URL: Bug Tracker, https://github.com/albertorc87/subir-paquete-pypi/issues
Author-email: antonioirles <antonioirles876@gmail.com>
License: MIT License
License-File: LICENSE
Classifier: License :: OSI Approved :: MIT License
Classifier: Operating System :: OS Independent
Classifier: Programming Language :: Python :: 3
Requires-Python: >=3.0
